{
	"first": [
		
		{
			"name": "JIRI SPORTS ONE",
			"image": "https://encrypted-tbn0.gstatic.com/images?q=tbn:ANd9GcS-z-jodxMHP8mjbUzwQEn9jFaJIly5jvHb4w&usqp=CAU",
			"news": "JIRI SPORTS ONE"
		},
		{
			"name": "JIRI SPORTS TWO",
			"image": "https://encrypted-tbn0.gstatic.com/images?q=tbn:ANd9GcS-z-jodxMHP8mjbUzwQEn9jFaJIly5jvHb4w&usqp=CAU",
			"news": "JIRI SPORTS TWO"
		},
		{
			"name": "JIRI SPORTS THREE",
			"image": "https://encrypted-tbn0.gstatic.com/images?q=tbn:ANd9GcS-z-jodxMHP8mjbUzwQEn9jFaJIly5jvHb4w&usqp=CAU",
			"news": "JIRI SPORTS THREE"
		},
		{
			"name": "JIRI SPORTS FOUR",
			"image": "https://encrypted-tbn0.gstatic.com/images?q=tbn:ANd9GcS-z-jodxMHP8mjbUzwQEn9jFaJIly5jvHb4w&usqp=CAU",
			"news": "JIRI SPORTS FOUR"
		},
		{
			"name": "JIRI SPORTS FIVE",
			"image": "https://encrypted-tbn0.gstatic.com/images?q=tbn:ANd9GcS-z-jodxMHP8mjbUzwQEn9jFaJIly5jvHb4w&usqp=CAU",
			"news": "JIRI SPORTS FIVE"
		}
	]

}
